ecsctl/__init__.py
ecsctl/__main__.py
ecsctl/alias.py
ecsctl/cmds.py
ecsctl/config.py
ecsctl/display.py
ecsctl/pty.py
ecsctl/wrapboto.py
ecsctl-20200907.dist-info/LICENSE
ecsctl-20200907.dist-info/METADATA
ecsctl-20200907.dist-info/WHEEL
ecsctl-20200907.dist-info/entry_points.txt
ecsctl-20200907.dist-info/top_level.txt
ecsctl-20200907.dist-info/RECORD
