Metadata-Version: 2.1
Name: ecsctl
Version: 20200907
Summary: kubectl-style command line client for AWS ECS.
Home-page: https://github.com/cxmcc/ecsctl
Author: Xiuming Chen
Author-email: cc@cxm.cc
License: UNKNOWN
Keywords: ECS,kubectl,AWS
Platform: UNKNOWN
Classifier: Development Status :: 4 - Beta
Classifier: Environment :: Console
Classifier: Topic :: System :: Clustering
Requires-Dist: boto3 (>=1.4.5)
Requires-Dist: click (>=6.7)
Requires-Dist: configparser (>=3.5.0)
Requires-Dist: docker (>=2.4.2)
Requires-Dist: dockerpty (>=0.4.1)
Requires-Dist: jsonpath (>=0.75)
Requires-Dist: tabulate (>=0.7.7)
Requires-Dist: humanize (>=0.5.1)
Requires-Dist: pytz (>=2017.2)
